espwifiarduino/__init__.py
espwifiarduino/ard_main.py
espwifiarduino-0.0.3.dist-info/METADATA
espwifiarduino-0.0.3.dist-info/WHEEL
espwifiarduino-0.0.3.dist-info/top_level.txt
espwifiarduino-0.0.3.dist-info/RECORD
